gdc_readgroups/__init__.py
gdc_readgroups/__main__.py
gdc_readgroups/exceptions.py
gdc_readgroups/extract_readgroup.py
gdc_readgroups/generate_template.py
gdc_readgroups/readgroup_template.json
gdc_readgroups/util.py
tests/__init__.py
tests/empty_rg_header_no_seq.py
tests/empty_rg_header_seq.py
tests/empty_rg_header_seq_reads.py
tests/rg_header_all_rg_tags.py
tests/rg_header_all_rg_tags_no_sq.py
tests/rg_header_conflicting_bc_pu2dot.py
tests/rg_header_invalid_pl.py
tests/rg_header_invalid_pm.py
tests/rg_header_no_id.py
tests/rg_header_only_id.py
tests/rg_header_pu0dot.py
tests/rg_header_pu1dot.py
tests/rg_header_pu2dot.py
tests/sam_file.py
tests/util.py
gdc_readgroups-0.4.dist-info/LICENSE
gdc_readgroups-0.4.dist-info/METADATA
gdc_readgroups-0.4.dist-info/WHEEL
gdc_readgroups-0.4.dist-info/entry_points.txt
gdc_readgroups-0.4.dist-info/top_level.txt
gdc_readgroups-0.4.dist-info/RECORD
