Metadata-Version: 2.1
Name: gdc-readgroups
Version: 0.4
Summary: From a BAM, convert each readgroup to a json/tsv object needed to create a GDC Read Group node.
Home-page: https://github.com/NCI-GDC/gdc-readgroups/
Author: Jeremiah H. Savage
Author-email: jeremiahsavage@gmail.com
License: UNKNOWN
Platform: UNKNOWN
Classifier: Development Status :: 4 - Beta
Classifier: Environment :: Console
Classifier: Intended Audience :: Developers
Classifier: License :: OSI Approved :: Apache Software License
Classifier: Operating System :: POSIX
Classifier: Programming Language :: Python :: 3
Classifier: Topic :: Scientific/Engineering :: Bio-Informatics
Requires-Dist: pysam (==0.15.2)
Requires-Dist: python-dateutil (==2.8.0)
